pvplib/__init__.py
pvplib/core.py
pvplib-0.3.2.dist-info/LICENSE
pvplib-0.3.2.dist-info/WHEEL
pvplib-0.3.2.dist-info/METADATA
pvplib-0.3.2.dist-info/RECORD
